odoo/addons/contract_sale_transmit_method/README.rst
odoo/addons/contract_sale_transmit_method/__init__.py
odoo/addons/contract_sale_transmit_method/__manifest__.py
odoo/addons/contract_sale_transmit_method/i18n/contract_sale_transmit_method.pot
odoo/addons/contract_sale_transmit_method/i18n/fr.po
odoo/addons/contract_sale_transmit_method/i18n/it.po
odoo/addons/contract_sale_transmit_method/models/__init__.py
odoo/addons/contract_sale_transmit_method/models/sale_order.py
odoo/addons/contract_sale_transmit_method/readme/CONTRIBUTORS.md
odoo/addons/contract_sale_transmit_method/readme/DESCRIPTION.md
odoo/addons/contract_sale_transmit_method/static/description/icon.png
odoo/addons/contract_sale_transmit_method/static/description/index.html
odoo/addons/contract_sale_transmit_method/tests/__init__.py
odoo/addons/contract_sale_transmit_method/tests/test_contract_sale_transmit_method.py
odoo_addon_contract_sale_transmit_method-18.0.1.0.0.6.dist-info/METADATA
odoo_addon_contract_sale_transmit_method-18.0.1.0.0.6.dist-info/WHEEL
odoo_addon_contract_sale_transmit_method-18.0.1.0.0.6.dist-info/top_level.txt
odoo_addon_contract_sale_transmit_method-18.0.1.0.0.6.dist-info/RECORD
