Metadata-Version: 2.1
Name: odoo-addon-contract_sale_transmit_method
Version: 18.0.1.0.0.6
Requires-Python: >=3.10
Requires-Dist: odoo-addon-contract_transmit_method==18.0.*
Requires-Dist: odoo-addon-product_contract==18.0.*
Requires-Dist: odoo-addon-sale_order_transmit_method==18.0.*
Requires-Dist: odoo==18.0.*
Summary: Propagate transmit method (email, post, portal, ...) from sale orders to contracts.
Home-page: https://github.com/OCA/contract
License: AGPL-3
Author: ACSONE SA/NV,Odoo Community Association (OCA)
Author-email: support@odoo-community.org
Classifier: Programming Language :: Python
Classifier: Framework :: Odoo
Classifier: Framework :: Odoo :: 18.0
Classifier: License :: OSI Approved :: GNU Affero General Public License v3
